ros_spdlog_vendor-1.7.0.data/data/share/ament_index/resource_index/package_run_dependencies/spdlog_vendor
ros_spdlog_vendor-1.7.0.data/data/share/ament_index/resource_index/packages/spdlog_vendor
ros_spdlog_vendor-1.7.0.data/data/share/ament_index/resource_index/parent_prefix_path/spdlog_vendor
ros_spdlog_vendor-1.7.0.data/data/share/spdlog_vendor/local_setup.bash
ros_spdlog_vendor-1.7.0.data/data/share/spdlog_vendor/local_setup.dsv
ros_spdlog_vendor-1.7.0.data/data/share/spdlog_vendor/local_setup.sh
ros_spdlog_vendor-1.7.0.data/data/share/spdlog_vendor/local_setup.zsh
ros_spdlog_vendor-1.7.0.data/data/share/spdlog_vendor/package.dsv
ros_spdlog_vendor-1.7.0.data/data/share/spdlog_vendor/package.xml
ros_spdlog_vendor-1.7.0.data/data/share/spdlog_vendor/cmake/spdlog_vendorConfig-version.cmake
ros_spdlog_vendor-1.7.0.data/data/share/spdlog_vendor/cmake/spdlog_vendorConfig.cmake
ros_spdlog_vendor-1.7.0.data/data/share/spdlog_vendor/environment/ament_prefix_path.dsv
ros_spdlog_vendor-1.7.0.data/data/share/spdlog_vendor/environment/ament_prefix_path.sh
ros_spdlog_vendor-1.7.0.data/data/share/spdlog_vendor/environment/path.dsv
ros_spdlog_vendor-1.7.0.data/data/share/spdlog_vendor/environment/path.sh
spdlog_vendor/_dummy.cpython-311-x86_64-linux-gnu.so
ros_spdlog_vendor-1.7.0.dist-info/METADATA
ros_spdlog_vendor-1.7.0.dist-info/WHEEL
ros_spdlog_vendor-1.7.0.dist-info/top_level.txt
ros_spdlog_vendor-1.7.0.dist-info/RECORD
ros_spdlog_vendor-1.7.0.dist-info/licenses/LICENSE
