Metadata-Version: 2.4
Name: ros-spdlog-vendor
Version: 1.7.0
Summary: ROS package providing a CMake shim for the high-performance spdlog logging library.
License-File: LICENSE
Dynamic: description
Dynamic: description-content-type
Dynamic: license-file
Dynamic: summary
